<annotation>
	<folder>baseOnCNN</folder>
	<filename>227.jpg</filename>
	<path>F:\111\hazePerson\baseOnCNN\227.jpg</path>
	<source>
		<database>Unknown</database>
	</source>
	<size>
		<width>169</width>
		<height>180</height>
		<depth>3</depth>
	</size>
	<segmented>0</segmented>
	<object>
		<name>person</name>
		<pose>Unspecified</pose>
		<truncated>0</truncated>
		<difficult>0</difficult>
		<bndbox>
			<xmin>65</xmin>
			<ymin>5</ymin>
			<xmax>123</xmax>
			<ymax>141</ymax>
		</bndbox>
	</object>
	<object>
		<name>person</name>
		<pose>Unspecified</pose>
		<truncated>0</truncated>
		<difficult>0</difficult>
		<bndbox>
			<xmin>117</xmin>
			<ymin>6</ymin>
			<xmax>159</xmax>
			<ymax>101</ymax>
		</bndbox>
	</object>
</annotation>
