<annotation>
	<folder>baseOnCNN</folder>
	<filename>460.jpg</filename>
	<path>F:\111\hazePerson\baseOnCNN\460.jpg</path>
	<source>
		<database>Unknown</database>
	</source>
	<size>
		<width>148</width>
		<height>141</height>
		<depth>3</depth>
	</size>
	<segmented>0</segmented>
	<object>
		<name>person</name>
		<pose>Unspecified</pose>
		<truncated>0</truncated>
		<difficult>0</difficult>
		<bndbox>
			<xmin>14</xmin>
			<ymin>21</ymin>
			<xmax>139</xmax>
			<ymax>66</ymax>
		</bndbox>
	</object>
</annotation>
