<annotation>
	<folder>PICTURES</folder>
	<filename>825.jpg</filename>
	<path>F:\my_project\pedestrain_detection_in_hazy\dataset1\PICTURES_LABELS_TRAIN\PICTURES\825.jpg</path>
	<source>
		<database>Unknown</database>
	</source>
	<size>
		<width>237</width>
		<height>226</height>
		<depth>3</depth>
	</size>
	<segmented>0</segmented>
	<object>
		<name>person</name>
		<pose>Unspecified</pose>
		<truncated>0</truncated>
		<difficult>0</difficult>
		<bndbox>
			<xmin>21</xmin>
			<ymin>53</ymin>
			<xmax>83</xmax>
			<ymax>217</ymax>
		</bndbox>
	</object>
	<object>
		<name>person</name>
		<pose>Unspecified</pose>
		<truncated>0</truncated>
		<difficult>0</difficult>
		<bndbox>
			<xmin>89</xmin>
			<ymin>47</ymin>
			<xmax>146</xmax>
			<ymax>215</ymax>
		</bndbox>
	</object>
	<object>
		<name>person</name>
		<pose>Unspecified</pose>
		<truncated>0</truncated>
		<difficult>0</difficult>
		<bndbox>
			<xmin>159</xmin>
			<ymin>49</ymin>
			<xmax>217</xmax>
			<ymax>214</ymax>
		</bndbox>
	</object>
	<object>
		<name>person</name>
		<pose>Unspecified</pose>
		<truncated>1</truncated>
		<difficult>0</difficult>
		<bndbox>
			<xmin>1</xmin>
			<ymin>91</ymin>
			<xmax>10</xmax>
			<ymax>124</ymax>
		</bndbox>
	</object>
	<object>
		<name>person</name>
		<pose>Unspecified</pose>
		<truncated>0</truncated>
		<difficult>0</difficult>
		<bndbox>
			<xmin>23</xmin>
			<ymin>96</ymin>
			<xmax>30</xmax>
			<ymax>122</ymax>
		</bndbox>
	</object>
	<object>
		<name>person</name>
		<pose>Unspecified</pose>
		<truncated>0</truncated>
		<difficult>0</difficult>
		<bndbox>
			<xmin>75</xmin>
			<ymin>88</ymin>
			<xmax>82</xmax>
			<ymax>121</ymax>
		</bndbox>
	</object>
	<object>
		<name>person</name>
		<pose>Unspecified</pose>
		<truncated>0</truncated>
		<difficult>0</difficult>
		<bndbox>
			<xmin>81</xmin>
			<ymin>91</ymin>
			<xmax>90</xmax>
			<ymax>122</ymax>
		</bndbox>
	</object>
	<object>
		<name>person</name>
		<pose>Unspecified</pose>
		<truncated>0</truncated>
		<difficult>0</difficult>
		<bndbox>
			<xmin>89</xmin>
			<ymin>40</ymin>
			<xmax>112</xmax>
			<ymax>73</ymax>
		</bndbox>
	</object>
	<object>
		<name>person</name>
		<pose>Unspecified</pose>
		<truncated>0</truncated>
		<difficult>0</difficult>
		<bndbox>
			<xmin>148</xmin>
			<ymin>92</ymin>
			<xmax>159</xmax>
			<ymax>123</ymax>
		</bndbox>
	</object>
</annotation>
