<annotation>
	<folder>baseOnCNN</folder>
	<filename>674.jpg</filename>
	<path>F:\111\hazePerson\baseOnCNN\674.jpg</path>
	<source>
		<database>Unknown</database>
	</source>
	<size>
		<width>230</width>
		<height>246</height>
		<depth>3</depth>
	</size>
	<segmented>0</segmented>
	<object>
		<name>person</name>
		<pose>Unspecified</pose>
		<truncated>0</truncated>
		<difficult>0</difficult>
		<bndbox>
			<xmin>27</xmin>
			<ymin>3</ymin>
			<xmax>75</xmax>
			<ymax>145</ymax>
		</bndbox>
	</object>
	<object>
		<name>person</name>
		<pose>Unspecified</pose>
		<truncated>0</truncated>
		<difficult>0</difficult>
		<bndbox>
			<xmin>82</xmin>
			<ymin>15</ymin>
			<xmax>112</xmax>
			<ymax>108</ymax>
		</bndbox>
	</object>
	<object>
		<name>person</name>
		<pose>Unspecified</pose>
		<truncated>0</truncated>
		<difficult>0</difficult>
		<bndbox>
			<xmin>103</xmin>
			<ymin>20</ymin>
			<xmax>132</xmax>
			<ymax>99</ymax>
		</bndbox>
	</object>
	<object>
		<name>person</name>
		<pose>Unspecified</pose>
		<truncated>0</truncated>
		<difficult>0</difficult>
		<bndbox>
			<xmin>197</xmin>
			<ymin>21</ymin>
			<xmax>220</xmax>
			<ymax>98</ymax>
		</bndbox>
	</object>
	<object>
		<name>person</name>
		<pose>Unspecified</pose>
		<truncated>0</truncated>
		<difficult>0</difficult>
		<bndbox>
			<xmin>132</xmin>
			<ymin>45</ymin>
			<xmax>196</xmax>
			<ymax>245</ymax>
		</bndbox>
	</object>
	<object>
		<name>person</name>
		<pose>Unspecified</pose>
		<truncated>0</truncated>
		<difficult>0</difficult>
		<bndbox>
			<xmin>12</xmin>
			<ymin>14</ymin>
			<xmax>35</xmax>
			<ymax>98</ymax>
		</bndbox>
	</object>
	<object>
		<name>person</name>
		<pose>Unspecified</pose>
		<truncated>0</truncated>
		<difficult>0</difficult>
		<bndbox>
			<xmin>69</xmin>
			<ymin>21</ymin>
			<xmax>89</xmax>
			<ymax>100</ymax>
		</bndbox>
	</object>
	<object>
		<name>person</name>
		<pose>Unspecified</pose>
		<truncated>0</truncated>
		<difficult>0</difficult>
		<bndbox>
			<xmin>134</xmin>
			<ymin>17</ymin>
			<xmax>155</xmax>
			<ymax>83</ymax>
		</bndbox>
	</object>
	<object>
		<name>person</name>
		<pose>Unspecified</pose>
		<truncated>0</truncated>
		<difficult>0</difficult>
		<bndbox>
			<xmin>161</xmin>
			<ymin>18</ymin>
			<xmax>187</xmax>
			<ymax>59</ymax>
		</bndbox>
	</object>
</annotation>
