<?xml version="1.0" ?>
<annotation>
	<folder>VOC2007</folder>
	<filename>crop001623.txt</filename>
	<source>
		<database>PASperson Database</database>
		<annotation>PASperson</annotation>
	</source>
	<size>
		<width>1083</width>
		<height>960</height>
		<depth>3</depth>
	</size>
	<segmented>0</segmented>
	<object>
		<name>person</name>
		<pose>Unspecified</pose>
		<truncated>0</truncated>
		<difficult>0</difficult>
		<bndbox>
			<xmin>612</xmin>
			<ymin>236</ymin>
			<xmax>780</xmax>
			<ymax>852</ymax>
		</bndbox>
	</object>
	<object>
		<name>person</name>
		<pose>Unspecified</pose>
		<truncated>0</truncated>
		<difficult>0</difficult>
		<bndbox>
			<xmin>499</xmin>
			<ymin>234</ymin>
			<xmax>618</xmax>
			<ymax>688</ymax>
		</bndbox>
	</object>
	<object>
		<name>person</name>
		<pose>Unspecified</pose>
		<truncated>0</truncated>
		<difficult>0</difficult>
		<bndbox>
			<xmin>305</xmin>
			<ymin>257</ymin>
			<xmax>497</xmax>
			<ymax>860</ymax>
		</bndbox>
	</object>
</annotation>
